{
    "pageid": 1133297,
    "ns": 0,
    "title": "Bashenga Unit (Earth-616)",
    "revisions": [
        {
            "slots": {
                "main": {
                    "contentmodel": "wikitext",
                    "contentformat": "text/x-wiki",
                    "*": "{{Marvel Database:Team Template\n| Image                   = Bashenga Unit (Earth-616) from Rise of the Black Panther Vol 1 1 001.jpg\n| Name                    = Bashenga Unit\n| EditorialNames          = \n| Aliases                 = \n\n| Status                  = Unknown\n| Identity                = Public\n| Reality                 = Earth-616\n| BaseOfOperations        = \n\n| Leaders                 = \n| CurrentMembers          = \n| FormerMembers           = \n| Allies                  = \n| Enemies                 = \n\n| Origin                  = \n| PlaceOfFormation        = \n| PlaceOfDissolution      = \n| Creators                = Evan Narcisse; Paul Renaud\n| First                   = Rise of the Black Panther Vol 1 1\n| Last                    = \n\n| HistoryText             = The Bashenga Unit was a squad of the [[Wakandan Army (Earth-616)|Wakandan Army]] deployed by King [[T'Chaka (Earth-616)|T'Chaka]] when [[Hydra (Earth-616)|Hydra]] forces led by [[Wolfgang von Strucker (Earth-616)|Baron Strucker]] attempted to push through the Wakandan border.{{r|Rise of the Black Panther Vol 1 1}}\n\n| Equipment               = \n| Transportation          = \n| Weapons                 = \n\n| Notes                   = * Named after [[Bashenga (Earth-616)|Bashenga]], the second known [[Black Panther]].{{r|Rise of the Black Panther Vol 1 1}}\n* Based on the color of their uniforms, the Bashenga Unit could've been the predecessor of the [[Hatut Zeraze (Earth-616)|Hatut Zeraze]].\n| Trivia                  = \n| Links                   = \n}}"
                }
            }
        }
    ],
    "page_id": "1133297"
}