{
    "pageid": 1201414,
    "ns": 0,
    "title": "Berserkers (Asgardian) (Earth-616)",
    "revisions": [
        {
            "slots": {
                "main": {
                    "contentmodel": "wikitext",
                    "contentformat": "text/x-wiki",
                    "*": "{{Marvel Database:Team Template\n| Image                   = Berserkers (Asgardians) (Earth-616) from Journey into Mystery Vol 1 647 001.jpg\n| Name                    = Berserkers\n| EditorialNames          = \n| Aliases                 = \n\n| Status                  = Active\n| Identity                = Public\n| Reality                 = Earth-616\n| BaseOfOperations        = \n\n| Leaders                 = \n| CurrentMembers          = [[Bodvar (Earth-616)|Bodvar]], [[Einhar (Earth-616)|Einhar]], [[Svip (Earth-616)|Svip]]\n| FormerMembers           = \n| Allies                  = [[Sif (Earth-616)|Lady Sif]]\n| Enemies                 = \n\n| Origin                  = \n| PlaceOfFormation        = \n| PlaceOfDissolution      = \n| Creators                = Kathryn Immonen; Valerio Schiti\n| First                   = Journey into Mystery Vol 1 647\n| Last                    = \n\n| HistoryText             = Exiled by [[Odin Borson (Earth-616)|Odin]] in some time in the distant past to a strange foreign land where they spend their lives killing and fighting against giant creatures and surreal monsters.\n\n| Equipment               = \n| Transportation          = \n| Weapons                 = \n\n| Notes                   = \n| Trivia                  = \n| Links                   = \n}}\n[[Category:Asgardian Organizations]]"
                }
            }
        }
    ],
    "page_id": "1201414"
}