{
    "pageid": 1099193,
    "ns": 0,
    "title": "Department of Internal Security (Earth-616)",
    "revisions": [
        {
            "slots": {
                "main": {
                    "contentmodel": "wikitext",
                    "contentformat": "text/x-wiki",
                    "*": "{{Marvel Database:Organization Template\n| Title                   = D.I.S.\n| Image                   = Department of Internal Security (Earth-616) from Spider-Man 2099 Vol 3 1 001.jpg\n| Name                    = Department of Internal Security\n| EditorialNames          = D.I.S.{{r|Spider-Man 2099 Vol 3 1}}\n| Aliases                 = \n\n| Status                  = Active\n| Identity                = Public\n| Reality                 = Earth-616\n| BaseOfOperations        = \n\n| Leaders                 = \n| CurrentMembers          = [[Walter Johnson (Earth-616)|Walter Johnson]]\n| FormerMembers           = \n| Allies                  = [[Alchemax (Earth-616)|Alchemax]]\n| Enemies                 = \n\n| Origin                  = \n| PlaceOfFormation        = \n| PlaceOfDissolution      = \n| Creators                = Peter David; William Sliney\n| First                   = Spider-Man 2099 Vol 3 1\n\n| History                 = The D.I.S. was a government agency that defended the citizens of the [[United States of America]] from terrorists. They backed [[Alchemax (Earth-616)|Alchemax]]'s [[Blackthorne Prison]] and in exchange, the D.I.S. could detain and interrogate their personal suspects.{{r|Spider-Man 2099 Vol 3 1}}\n| Equipment               = \n| Transportation          = \n| Weapons                 = \n| Notes                   = \n| Trivia                  = \n| Links                   = \n}}\n[[Category:Government Organizations]]"
                }
            }
        }
    ],
    "page_id": "1099193"
}