{
    "pageid": 1054408,
    "ns": 0,
    "title": "Eternity Watch (Earth-616)",
    "revisions": [
        {
            "slots": {
                "main": {
                    "contentmodel": "wikitext",
                    "contentformat": "text/x-wiki",
                    "*": "{{Marvel Database:Team Template\n| Image                   = Eternity Watch (Earth-616) from Ultimates 2 Vol 2 9 001.jpg\n| ImageSize               = 250px\n| Name                    = Eternity Watch\n| EditorialNames          = \n| Aliases                 = \n\n| Status                  = Active\n| Identity                = Secret\n| Reality                 = Earth-616\n| BaseOfOperations        = [[Taa III]]\n\n| Leaders                 = [[Galan (Earth-616)|Galactus]]\n| CurrentMembers          = [[Infinaut (Earth-616)|Infinaut]], [[Emmett Proudhawk (Earth-616)|Psi-Hawk]], [[Egros (Earth-616)|Ego-Prime]]\n| FormerMembers           = [[Shaper of Worlds (Earth-616)|Shaper of Worlds]]\n| Allies                  = [[Ultimates (Earth-616)]], [[Ultimates (Multiverse)]]\n| Enemies                 = [[First Firmament (First Cosmos)|First Firmament]]\n\n| Origin                  = \n| PlaceOfFormation        = [[Taa III]]\n| PlaceOfDissolution      = \n| Creators                = Al Ewing; Aud Koch\n| First                   = Ultimates 2 Vol 2 8\n| Last                    = \n\n| HistoryText             = The Eternity Watch is a group of powerful beings gathered by [[Galan (Earth-616)|Galactus]] to help him save [[Eternity (Multiverse)|the multiversal personification of Eternity]] from his captor: the [[First Firmament (First Cosmos)|First Firmament]], the first iteration of all that is.{{r|Ultimates 2 Vol 2 8}}\n\n| Equipment               = \n| Transportation          = \n| Weapons                 = \n\n| Notes                   = \n| Trivia                  = \n| Links                   = \n}}"
                }
            }
        }
    ],
    "page_id": "1054408"
}