{
    "pageid": 20749,
    "ns": 0,
    "title": "Fathom Five (Earth-616)",
    "revisions": [
        {
            "slots": {
                "main": {
                    "contentmodel": "wikitext",
                    "contentformat": "text/x-wiki",
                    "*": "{{Marvel Database:Team Template\n| Image                   = Fathom Five (Earth-616) from New Thunderbolts Vol 1 1 0001.png\n| Name                    = Fathom Five\n| Aliases                 = \n\n| Status                  = Defunct\n| Identity                = Secret\n| Reality                 = Earth-616\n| BaseOfOperations        = an unknown At'la'tique undersea base\n\n| Leaders                 = \n| CurrentMembers          = [[Llyron McKenzie (Earth-616)|Llyron]], [[Bloodtide (Atlantean) (Earth-616)|Bloodtide]], [[Dragonrider (Earth-616)|Dragonrider]], [[Manowar (Earth-616)|Manowar]], [[Sea Leopard (Earth-616)|Sea Leopard]]\n| FormerMembers           = \n| Allies                  = [[Nagala]]\n| Enemies                 = [[Namor McKenzie (Earth-616)|Namor the Sub-Mariner]]\n\n| Origin                  = Atlantean terrorist group\n| PlaceOfFormation        = \n| PlaceOfDissolution      = \n| Creators                = Fabian Nicieza; Kurt Busiek; Tom Grummett\n| First                   = New Thunderbolts Vol 1 1\n| Last                    = \n\n| HistoryText             = The Fathom Five, was a militant Atlantean splinter group determined to destroy humanity. They were a strike force formed from the [[At'La'Tique (Earth-616)|\"Fury of the Sea\"]], a group of undersea terrorists who seek to destroy air-breathers. The team consisted of [[Llyron McKenzie (Earth-616)|Llyron]], [[Bloodtide (Atlantean) (Earth-616)|Bloodtide]], [[Dragonrider (Earth-616)|Dragonrider]], [[Manowar (Earth-616)|Manowar]], and [[Sea Leopard (Earth-616)|Sea Leopard]]. To meet their goals, they even went as far to team up with [[Wolfgang von Strucker (Earth-616)|Baron Strucker]] and [[Hydra (Earth-616)|Hydra]].{{r|New Thunderbolts Vol 1 3}} The team later attacked the Persian Gulf and the coast of China.{{r|New Thunderbolts Vol 1 2}}\n\nIn an attempt to destroy all surface life, the team attacked New York. They attacked and lashed out any one they met in the streets. The Thunderbolts counteracted the team, forcing the Fathom Five to retreat.{{r|New Thunderbolts Vol 1 1}} After repulsing a force of Atlanteans sent to capture them,{{r|New Thunderbolts Vol 1 3}} the Fathom Five attacked New York again. The Thunderbolts against opposed them, and after a long battle, the Five were defeated. Llyron and Sea Leopard managed to escape. Bloodtide, Dragonrider, and Manowar were taken into custody.{{r|New Thunderbolts Vol 1 3|5}}\n\nLlyron was nearly killed by the [[Chen Lu (Earth-616)|Radioactive Man]] and tossed into the water unconscious.{{r|New Thunderbolts Vol 1 6}} He was arrested by the Atlanteans and was returned to Atlantis, only to discover that he had radiation poisoning, and furthermore, had spread the poisoning among the Atlantean population.{{r|New Thunderbolts Vol 1 9}}\n\n| Equipment               = \n| Transportation          = \n| Weapons                 = \n\n| Notes                   = \n| Trivia                  = \n| Links                   = \n* http://www.marvunapp.com/Appendix3/fathomfivetbolts.htm\n* http://www.marvel.com/universe/Fathom_Five\n* http://en.wikipedia.org/wiki/Fathom_Five_(comics)\n}}"
                }
            }
        }
    ],
    "page_id": "20749"
}