{
    "pageid": 1339535,
    "ns": 0,
    "title": "Future Avengers (Earth-616)",
    "revisions": [
        {
            "slots": {
                "main": {
                    "contentmodel": "wikitext",
                    "contentformat": "text/x-wiki",
                    "*": "{{Marvel Database:Team Template\n| Image                   = Future Avengers (Earth-616) from Future Fight Firsts Crescent and Io Vol 1 1 001.jpg\n| Name                    = Future Avengers\n| Aliases                 = \n\n| Status                  = Active\n| Identity                = Secret \n| Reality                 = Earth-616\n| BaseOfOperations        = [[Tokyo]]\n\n| Leaders                 = \n| CurrentMembers          = [[Actress (Chloe) (Earth-616)|Actress (Chloe)]]; [[Adi (Earth-616)|Codec (Adi)]]; [[Hurricane (Makoto) (Earth-616)|Hurricane (Makoto)]], [[Twister (Bruno)]];\n| FormerMembers           = \n| Allies                  = formerly [[Hydra (Earth-616)|Hydra]]\n| Enemies                 = [[Hydra (Earth-616)|Hydra]]\n\n| Origin                  = Reformed ex-Hydra trainees\n| PlaceOfFormation        = \n| PlaceOfDissolution      = \n| Creators                = Alyssa Wong; Alejandro Garza\n| First                   = Future Fight Firsts: White Fox #1\n| Last                    = \n\n| HistoryText             = The Future Avengers are a group of young heroes that were raised by [[Hydra (Earth-616)|Hydra]] to fight the [[Avengers (Earth-616)|Avengers]]. When they discovered that it was actually Hydra that was evil, they betrayed the cause and became heroes.{{r|Future Fight Firsts: White Fox #1}}\n\n| Equipment               = \n| Transportation          = \n| Weapons                 = \n\n| Notes                   = \n| Trivia                  = * The Future Avengers are based off of the main characters of the Marvel/MADHOUSE anime production ''Marvel Future Avengers''. The series premiered on the Disney+ streaming service on February 28th, 2020, two months after their comic appearance.\n| Links                   = \n}}\n[[Category:Content Adapted from Other Media]]"
                }
            }
        }
    ],
    "page_id": "1339535"
}