{
    "pageid": 1433103,
    "ns": 0,
    "title": "Gambello Family (Earth-616)",
    "revisions": [
        {
            "slots": {
                "main": {
                    "contentmodel": "wikitext",
                    "contentformat": "text/x-wiki",
                    "*": "{{Marvel Database:Team Template\n| Image                   = Gambello_Family_(Earth-616)_from_Punisher_War_Zone_Vol_1_21.png\n| Name                    = \n| Title                   = Gambello Family\n| EditorialNames          = \n| Aliases                 = \n\n| Status                  = Active\n| Identity                = Public\n| Reality                 = Earth-616\n| BaseOfOperations        = \n\n| Leaders                 = \n| CurrentMembers          = \n| FormerMembers           = \n| Allies                  = \n| Enemies                 = [[Frank Castle (Earth-616)|Punisher]], [[Dennis Xavier Hanrahan (Earth-616)|D.X. Hanrahan]]\n\n| Origin                  = \n| PlaceOfFormation        = \n| PlaceOfDefunction       = \n| Creators                = Larry Hama; Hoang Nguyen\n| First                   = Punisher: War Zone Vol 1 20\n| Last                    = \n\n| HistoryText             = The Gambello Family were a crime family that were distributors for a drug pipeline that originated in [[Madripoor]]. Their ranks and operations were being hit by [[Dennis Xavier Hanrahan (Earth-616)|D.X. Hanrahan]] a psychotic hitman and former Vietnam War veteran, who was working for [[Nguyen Ngoc Coy (Earth-616)|General Coy]].{{r|Punisher: War Zone Vol 1 20|21}}\n\n| Equipment               = \n| Transportation          = \n| Weapons                 = \n\n| Notes                   = \n| Trivia                  = \n| Links                   = \n}}\n[[Category:Criminal Organizations]]\n[[Category:Cosa Nostra]]\n[[Category:Italian Organizations]]\n[[Category:Crime Families]]"
                }
            }
        }
    ],
    "page_id": "1433103"
}