{
    "pageid": 15718,
    "ns": 0,
    "title": "Grand Inquisitors (Earth-616)",
    "revisions": [
        {
            "slots": {
                "main": {
                    "contentmodel": "wikitext",
                    "contentformat": "text/x-wiki",
                    "*": "{{Marvel Database:Team Template\n| Image                   = \n| Name                    = Grand Inquisitors\n| Aliases                 = \n\n| Status                  = Defunct\n| Identity                = \n| Reality                 = Earth-616\n| BaseOfOperations        = \n\n| Leaders                 = \n| CurrentMembers          = [[Borgia (Roclite) (Earth-616)|Borgia]]\n| FormerMembers           = \n| Allies                  = [[Universal Church of Truth]]\n| Enemies                 = [[Adam Warlock (Earth-616)|Adam Warlock]]\n\n| Origin                  = Agents of the [[Universal Church of Truth]]\n| PlaceOfFormation        = \n| PlaceOfDissolution      = \n| Creators                = Jim Starlin\n| First                   = Strange Tales #178\n| Last                    = \n\n| HistoryText             = \n\n| Equipment               = \n| Transportation          = \n| Weapons                 = \n\n| Notes                   = \n| Trivia                  = \n| Links                   = \n}}\n[[Category:Jim Starlin/Creator]]"
                }
            }
        }
    ],
    "page_id": "15718"
}