{
    "pageid": 522712,
    "ns": 0,
    "title": "Mad Squad (Earth-616)",
    "revisions": [
        {
            "slots": {
                "main": {
                    "contentmodel": "wikitext",
                    "contentformat": "text/x-wiki",
                    "*": "{{Marvel Database:Team Template\n| Image                   = Mad Squad (Earth-616) 001.JPG\n| Name                    = Mad Squad\n| Aliases                 = \n\n| Status                  = Active\n| Identity                = Known to Authorities\n\n| Reality                 = 616\n| BaseOfOperations        = \n\n| Leaders                 = [[Amanda von Doom (Earth-616)|Commander Amanda von Doom]]\n| CurrentMembers          = [[Hulked-Out Monkey (Earth-616)|Bridge]], [[Mister Gor (Earth-616)|Mister Gor]]\n| FormerMembers           = [[B.R.A.I.N. (Earth-616)|B.R.A.I.N.]]\n| Allies                  = [[Bruce Banner (Earth-616)|Hulk]]\n| Enemies                 = [[Bruce Banner (Earth-616)|Bruce Banner]]\n\n| Origin                  = \n| PlaceOfFormation        = \n| PlaceOfDissolution      = \n| Creators                = Jason Aaron; Marc Silvestri\n| First                   = Incredible Hulk Vol 3 2\n| Last                    = \n\n| HistoryText             = A government-sponsored team lead by [[Amanda von Doom (Earth-616)|Commander von Doom]] with the mission to hunt down dangerous and amoral scientists.\n\n| Equipment               = \n| Transportation          = \n| Weapons                 = \n\n| Notes                   = \n| Trivia                  = \n| Links                   = \n}}"
                }
            }
        }
    ],
    "page_id": "522712"
}