{
    "pageid": 2984,
    "ns": 0,
    "title": "Mys-Tech (Earth-616)",
    "revisions": [
        {
            "slots": {
                "main": {
                    "contentmodel": "wikitext",
                    "contentformat": "text/x-wiki",
                    "*": "{{Marvel Database:Organization Template\n| Image                   = Mys-Tech (Earth-616) from S.H.I.E.L.D. Vol 3 5 001.png\n| Name                    = [[Mys-Tech]]\n| Aliases                 = (Mys-Tech Board:) Techno-Wizards,{{citation}} Sect of Chasm,{{citation}} Sect of Chasdim{{r|Marvel Atlas #1|; [[United Kingdom]]'s entry}}\n\n| Leaders                = [[Algernon Crowe (Earth-616)|Algernon Crowe]], [[Bronwen Gryffn (Earth-616)|Bronwen Gryffn]], [[Eadmund Porlock (Earth-616)|Eadmund Porlock]], [[Brendan Rathcoole (Earth-616)|Brendan Rathcoole]], [[Gudrun Tyburn (Earth-616)|Gudrun Tyburn]], [[Ormond Wychwood (Earth-616)|Ormond Wychwood]]\n| CurrentMembers          = Atkinson, [[Bysshe (Earth-616)|Bysshe]], [[D.O.G.S. (Earth-616)|D.O.G.S.]], [[Sidney Fishburne (Earth-616)|Sidney Fishburne]], [[Gadafel (Earth-616)|Gadafel]], A. Grant, [[H.A.R.P.I.E.S. (Earth-616)|H.A.R.P.I.E.S.]], [[Albert Potter (Earth-616)|Hurricane (Albert Potter)]], [[Jack the Pantherine (Earth-616)|Jack the Pantherine]], Jenkins, Laarson, Mr. Lee, [[Magpie (Earth-616)|Magpie]], [[Mainstream (Earth-616)|Mainstream]], [[Oonagh Mullarkey (Earth-616)|Oonagh Mullarkey (Plasmer)]], [[Psycho-Warriors (Earth-616)|Psycho-Warriors]], [[Psycho-Wraiths (Earth-616)|Psycho-Wraiths]], Commander Ritinski, [[Sisters of Grace (Earth-616)|Sisters of Grace]], Skire, Skyler, [[Ethan Slaughter (Earth-616)|Ethan Slaughter]], [[Slaugherhouse Six (Earth-616)|Slaugherhouse Six]], [[Suyin (Earth-616)|Suyin]], [[Character Index/T#Taylor|Taylor]], [[Tektos (Earth-616)|Tektos]], [[Sarah Townsend (Earth-616)|Sarah Townsend]], Webb, [[Character Index/S#Sanders|Sanders]]\n| FormerMembers           = [[Anti-Being (Earth-616)|Anti-Being]], [[Collapsar (Earth-616)|Collapsar]], [[Jonathan Bryant (Digitek) (Earth-616)|Digitek]], [[Daniel Jones (Earth-616)|G-Force]], [[Ranulph Haldane (Earth-616)|Ranulph Haldane]] (former Board member), [[Breeze James (Earth-616)|Breeze James]], [[Julius Mullarkey (Earth-616)|Killpower]], V. Matthews, [[Corrine Walton (Earth-616)|Panther]], [[Permafrost (Earth-616)|Permafrost]], [[Sunder (Mys-Tech Agent) (Earth-616)|Sunder]]\n\n| Identity                = Secret\n| Affiliation             =\n| Allies                  = [[Gena-Sys (Earth-616)|Gena-Sys]], [[Nakasoni Corporation (Earth-616)|Nakasoni Corporation]], [[Omni Corporation (Earth-616)|Omni Corporation]]\n| Enemies                 = [[Abadon (Earth-616)|Abadon]], [[Aftermath (Sleeper) (Earth-616)|Aftermath]], [[Shevaun Haldane (Earth-616)|Dark Angel]], [[Dark Guard (Earth-616)|Dark Guard]], [[Death Metal (Earth-8410)|Death Metal]], [[Minion (Earth-8410)|Minion]], [[Czorn Yson (Earth-616)|Die-Cut]], [[Encoders (Dark Angel Allies)|Encoders]], [[Excalibur (Earth-616)|Excalibur]], [[Fantastic Four (Earth-616)|Fantastic Four]], [[Nicholas Fury (Earth-616)|Nick Fury]], [[Gene Dogs (Earth-616)|Gene Dogs]], [[Genetix (Earth-616)|Genetix]], [[Guide (Earth-616)|Guide]], [[Kether Troop (Earth-616)|Kether Troop]], [[Julius Mullarkey (Earth-616)|Killpower]], [[Knights of Pendragon (Earth-616)|Knights of Pendragon]], [[Model Soldiers (Earth-616)|Model Soldiers]], [[Harley Davidson (Earth-616)|Motormouth]], [[Elizabeth Braddock (Earth-616)|Psylocke]], [[Shadow Riders (Earth-616)|Shadow Riders]], [[Peter Parker (Earth-616)|Spider-Man]], [[Special Task Force Omega Response Mandate (Earth-616)|S.T.O.R.M.]], [[Tuck (Earth-8410)|Tuck]], [[Wyrd Sisters (Earth-616)|Wyrd Sisters]], [[X-Factor (Earth-616)|X-Factor]], [[X-Men (Earth-616)|X-Men]]\n\n| Origin                  = \n| Reality                 = Earth-616\n| Status                  = Active\n| BaseOfOperations        = [[Mys-Tech Building]], [[London (England)|London]], [[England]], [[United Kingdom]]\n| PlaceOfFormation        = \n| PlaceOfDissolution      = \n\n| Creators                = Nick Vince; Gary Erskine\n| First                   = Warheads Vol 1 1\n| History                 = \n===Overview===\n'''Mys-Tech'''  is an [[United Kingdom|British]] multinational chemical corporation with worldwide interests. It is headquartered in [[London (England)|London]], [[UK]]. Mys-Tech employs thousands people with facilities all over the world.\n\n===Origin===\nIn the year 987, A.D. seven members of a druid cult made a deal with the demon [[Mephisto (Earth-616)|Mephisto]]: in exchange for immortality, they agreed to funnel souls into [[Mephisto's Realm]].{{R|Warheads Vol 1 1}}\n\nOver the subsequent millennium, the mages acquired great wealth and became the board members a London-based corporation named Mys-Tech. To pay their debt to Mephisto, the Mys-Tech board plotted to take over the world and kill vast numbers of innocents.{{R|Warheads Vol 1 1}}\n\n===Modern Era===\nTheir assets included the Un-Earth, a model of the planet that operated like a voodoo doll, and the Warheads, mercenaries who could travel through wormholes to other dimensions or times. The board members eventually transformed themselves into beings of even greater power known as the Techno-Wizards.{{r|Warheads #1}}\n| Equipment               = \n| Transportation          = \n| Weapons                 = \n| Notes                   = \n| Trivia                  = \n| Links                   = \n}}\n[[Category:Terrorist Organizations]]\n[[Category:Companies]]\n[[Category:Mystical Organizations]]\n[[Category:Marvel UK Characters]]\n[[Category:British Organizations]]\n[[Category:Criminal Organizations]]"
                }
            }
        }
    ],
    "page_id": "2984"
}