{
    "pageid": 1114996,
    "ns": 0,
    "title": "New York Mets (Earth-616)",
    "revisions": [
        {
            "slots": {
                "main": {
                    "contentmodel": "wikitext",
                    "contentformat": "text/x-wiki",
                    "*": "{{Marvel Database:Team Template\n| Image                   = New_York_Mets_(Earth-616)_from_Peter_Parker_Spider-Man_Vol_1_33_001.jpg\n| Name                    = New York Mets\n| Aliases                 = \n\n| Status                  = Active\n| Identity                = Public\n| Reality                 = Earth-616\n| BaseOfOperations        = [[Shea Stadium]], [[Queens]], [[New York City]]\n| OrganizationLeaders             = \n| CurrentMembers          = \n| FormerMembers           = \n| Allies                  = [[Peter Parker (Earth-616)|Peter Parker]] (fan) [[Benjamin Parker (Earth-616)|Ben Parker]] (fan)\n| Enemies                 = \n\n| Origin                  = Baseball Team \n| PlaceOfFormation        = \n| PlaceOfDissolution      = \n| Creators                = \n| First                   = Peter Parker: Spider-Man Vol 1 33 \n| Last                    = \n\n| HistoryText             = \n===Overview===\nThe '''New York Mets''' are an [[American]] professional baseball team based in [[Queens]], [[New York City]]. The Mets compete in Major League Baseball. The Mets are one of two Major League clubs based in New York City; the other is the [[New York Yankees (Earth-616)|New York Yankees]]. The team was formed in 1962 to replace the [[Brooklyn Dodgers]]. \n\n===Events===\n[[Benjamin Parker (Earth-616)|Ben Parker]] a Queens native used to take his nephew [[Peter Parker (Earth-616)|Peter Parker]] to see Shea Stadium to view the Mets. This made Peter a long Mets fan. In Peter\u2019s own words, the Mets are \u201ca bunch of loveable losers who hit the occasional home run by accident.\u201d{{r|Peter Parker: Spider-Man Vol 1 33}}\n\n| Equipment               = \n| Transportation          = \n| Weapons                 = \n| Notes                   = \n| Trivia                  = \n| Links                   = \n}}\n[[Category:Baseball Teams]]\n[[Category:Historical Organizations]]"
                }
            }
        }
    ],
    "page_id": "1114996"
}