{
    "pageid": 1189373,
    "ns": 0,
    "title": "New York Giants (Earth-616)",
    "revisions": [
        {
            "slots": {
                "main": {
                    "contentmodel": "wikitext",
                    "contentformat": "text/x-wiki",
                    "*": "{{Marvel Database:Team Template\n| Image                   = New York Giants (Earth-616) from NFL Superpro Vol 1 5 0001.jpg\n| Name                    = [[New York Giants]]\n| EditorialNames          = [[New York Giants]]\n| Aliases                 = <nowiki></nowiki>\n\n| Status                  = Active\n| Alignment               = \n| Identity                = Public\n| Reality                 = Earth-616\n| BaseOfOperations        = [[New York City]], [[New York (State)|New York]]\n\n| Leaders                 = \n| CurrentMembers          = [[Lawrence Taylor (Earth-616)|Lawrence Taylor]], [[Phillip Simms (Earth-616)|Phil Simms]], [[Carl Banks (Earth-616)|Carl Banks]], [[Tim Pressman (Earth-616)|Tim Pressman]]\n| FormerMembers           = [[Fat Cobra (Earth-616)|Fat Cobra]]\n| Allies                  = [[Phil Grayfield (Earth-616)|Superpro]]\n| Enemies                 = Head Hunters\n\n| Origin                  = Professional football team\n| PlaceOfFormation        = \n| PlaceOfDissolution      = \n| Creators                = Fabian Nicieza; Jose Delbo\n| First                   = NFL Superpro Vol 1 4\n| Last                    = \n\n| HistoryText             = The '''New York Giants''' are a professional American football team based in the New York metropolitan area. The Giants compete in the NFL (National Football League). The team plays its home games at [[MetLife Stadium]] in [[East Rutherford]], [[New Jersey (State)|New Jersey]]. \n\n[[File:Fat_Cobra_(Earth-616)_from_Immortal_Weapons_Vol_1_1_0005.jpg|left|thumb]]\nIn the mid 20th century; [[Fat Cobra (Earth-616)|Fat Cobra]] played defensive end for the Giants for two seasons until the league kicked him out for seriously wounding several protesters from the [[Ku Klux Klan (Earth-616)|Ku Klux Klan]].{{r|Immortal Weapons Vol 1 1}}\n\n| Equipment               = \n| Transportation          = \n| Weapons                 = \n\n| Notes                   = \n| Trivia                  = \n| Links                   = https://en.wikipedia.org/wiki/New_York_Giants\n}}\n[[Category:American Football Teams]]\n[[Category:Historical Organizations]]"
                }
            }
        }
    ],
    "page_id": "1189373"
}