{
    "pageid": 95512,
    "ns": 0,
    "title": "Ricadonna's Rogues (Earth-616)",
    "revisions": [
        {
            "slots": {
                "main": {
                    "contentmodel": "wikitext",
                    "contentformat": "text/x-wiki",
                    "*": "{{Marvel Database:Team Template\n| Image                   = \n| Name                    = Ricadonna's Rogues\n| Aliases                 = \n\n| Status                  = \n| Identity                = \n| Reality                 = Earth-616\n| BaseOfOperations        = \n\n| Leaders                 = [[Celia Ricadonna (Earth-616)|Ricadonna]]\n| CurrentMembers          = [[Kingsize (Earth-616)|Kingsize]], [[Fera (Earth-616)|Ferocia]], [[Dan Springer (Earth-616)|Flame]], [[Jonathan Swift (Earth-616)|Blue Streak]]\n| FormerMembers           = \n| Allies                  = \n| Enemies                 = \n\n| Origin                  = \n| PlaceOfFormation        = \n| PlaceOfDissolution      = \n| Creators                = Justin Gray; Jimmy Palmiotti; Francis Portela; Billy Tucci\n| First                   = Heroes for Hire Vol 2 #3\n| Last                    = \n\n| HistoryText             = Ricadonna transplanted Skrull organs into variouse human supervillians only four survived the transplant and became known as Ricadonna's Rogues\n\n| Equipment               = \n| Transportation          = \n| Weapons                 = \n\n| Notes                   = \n| Trivia                  = \n| Links                   = \n}}"
                }
            }
        }
    ],
    "page_id": "95512"
}