{
    "pageid": 519094,
    "ns": 0,
    "title": "Worldform, Inc. (Earth-616)",
    "revisions": [
        {
            "slots": {
                "main": {
                    "contentmodel": "wikitext",
                    "contentformat": "text/x-wiki",
                    "*": "{{Marvel Database:Organization Template\n| Image                   = Worldform, Inc. (Earth-616) from Iron Man Vol 1 37 001.jpg\n| Name                    = Worldform, Inc.\n| Aliases                 = \n\n| Leaders                         = \n| CurrentMembers          = [[Klark (Earth-616)|Klark]]; C-1; [[Changers (Earth-616)|Changers]] (probably other units are active)\n| FormerMembers           = [[Foreman (Earth-616)|Foreman]]; [[Ramrod (Alien) (Earth-616)|Ramrod]]\n\n| Identity                = Secret\n| Affiliation             =\n| Allies                  = \n| Enemies                 = [[Anthony Stark (Earth-616)|Iron Man]]\n\n| Origin                  = \n| Reality                 = Earth-616\n| Status                  = Active\n| BaseOfOperations        = Outside Earth\n| PlaceOfFormation        = Outside Earth\n| PlaceOfDissolution      = \n\n| Creators                = Gerry Conway; Don Heck\n| First                   = Iron Man Vol 1 37\n\n| History                 = Worldform, Inc is a planetary engineering corporation which rebuilds worlds to the specifications of their clients. Even if the planet is already populated, they will exterminate its inhabitants to customize the world.{{r|Iron Man Vol 1 37}} It is apparently active throughout the galaxy and one of its androids [[Ramrod (Alien) (Earth-616)|Ramrod]] had visited a thousand worlds in its service to Worldform, Inc.{{r|Iron Man Vol 1 36}} They were contracted by a race whose sun had gone supernova which needed a world with a glass-like surface. Worldform, Inc. had no such world but selected Earth and sent four of their \"Doom-Carrier\" robots to flatten the Earth which were stopped by [[Anthony Stark (Earth-616)|Iron Man]].{{r|Iron Man Vol 1 37}}\n| Equipment               = \n| Transportation          = Spaceships\n| Weapons                 = Androids\n| Notes                   = \n| Trivia                  = \n| Links                   = \n}}\n\n[[Category: Interplanetary Organizations]][[Category: Companies]]"
                }
            }
        }
    ],
    "page_id": "519094"
}